openwholeslide/__init__.py
openwholeslide/__version__.py
openwholeslide/_slide.py
openwholeslide/vectors.py
openwholeslide/wsi.py
openwholeslide-0.3.6.dist-info/LICENSE
openwholeslide-0.3.6.dist-info/METADATA
openwholeslide-0.3.6.dist-info/WHEEL
openwholeslide-0.3.6.dist-info/top_level.txt
openwholeslide-0.3.6.dist-info/RECORD
