Metadata-Version: 2.1
Name: openwholeslide
Version: 0.3.6
Summary: Wrapper around tifffile library to have the same API as OpenSlide.
Home-page: https://gitlab.com/prother-wal_ulb_lis_mnu/openwholeslide
Author: Arthur Elskens, Adrien Foucart
Author-email: arthur.elskens@ulb.be, adrien.foucart@ulb.be
License: MIT
Project-URL: GitHub, https://gitlab.com/prother-wal_ulb_lis_mnu/openwholeslide
Project-URL: Tracker, https://gitlab.com/prother-wal_ulb_lis_mnu/openwholeslide/issues
Classifier: License :: OSI Approved :: MIT License
Classifier: Programming Language :: Python
Classifier: Programming Language :: Python :: 3
Classifier: Programming Language :: Python :: 3.8
Classifier: Programming Language :: Python :: Implementation :: CPython
Classifier: Programming Language :: Python :: Implementation :: PyPy
Requires-Python: >=3.8
License-File: LICENSE
Requires-Dist: imagecodecs>=2023.7.10
Requires-Dist: numpy>=1.23.5
Requires-Dist: Pillow>=9.4.0
Requires-Dist: scikit-image>=0.19.3
Requires-Dist: SimpleITK>=2.2.1
Requires-Dist: tifffile>=2023.1.23.1
